vidtoolz_concat/__init__.py
vidtoolz_concat-0.0.3.dist-info/licenses/LICENSE
vidtoolz_concat-0.0.3.dist-info/METADATA
vidtoolz_concat-0.0.3.dist-info/WHEEL
vidtoolz_concat-0.0.3.dist-info/entry_points.txt
vidtoolz_concat-0.0.3.dist-info/top_level.txt
vidtoolz_concat-0.0.3.dist-info/RECORD
