Metadata-Version: 2.4
Name: vidtoolz-concat
Version: 0.0.3
Summary: Concat videos using ffmpeg 
Author: Sukhbinder Singh
License: Apache-2.0
Project-URL: Homepage, https://github.com/sukhbinder/vidtoolz-concat
Project-URL: Changelog, https://github.com/sukhbinder/vidtoolz-concat/releases
Project-URL: Issues, https://github.com/sukhbinder/vidtoolz-concat/issues
Project-URL: CI, https://github.com/sukhbinder/vidtoolz-concat/actions
Classifier: License :: OSI Approved :: Apache Software License
License-File: LICENSE
Requires-Dist: vidtoolz
Requires-Dist: numpy
Provides-Extra: test
Requires-Dist: pytest; extra == "test"
Dynamic: license-file
